{
  "subject": "ADV",
  "scrapedAt": "2026-05-25T21:18:01.986Z",
  "catalogYear": "2025-2026",
  "courses": [
    {
      "code": "ADV 2034",
      "subject": "ADV",
      "number": "2034",
      "level": 2000,
      "title": "Visual Communication Strategies",
      "credits": {
        "min": 3,
        "max": 3
      },
      "isVariableCredit": false,
      "description": "Concepts and techniques of visual storytelling for corporate and commercial communication through paid, earned, shared, and owned media. Design and production of visual messages for delivery through print, photography, videography, and online channels. Analysis of effective visual communication in advertising and public relations campaigns. Ethical consideration of visual communication choices. Pre: Sophomore standing",
      "prerequisites": {
        "rawText": "COMM 1016 or ENGL 1106 or ENGL 1204H",
        "referencedCourses": [
          "COMM 1016",
          "ENGL 1106"
        ]
      },
      "pathwaysConcepts": [],
      "contactHours": "(3 Lec, 3 Crd)",
      "crossListedWith": [],
      "sourceUrl": "https://catalog.vt.edu/undergraduate/course-descriptions/adv/",
      "catalogYear": "2025-2026"
    },
    {
      "code": "ADV 2134",
      "subject": "ADV",
      "number": "2134",
      "level": 2000,
      "title": "Introduction to Health Communication",
      "credits": {
        "min": 3,
        "max": 3
      },
      "isVariableCredit": false,
      "description": "Introduction to health communication with a focus on current issues and perspectives, including patient-provider communication, cultural conceptions of health and illness, media portrayals of health, communication in health organizations, health communication theories, information technologies in health communication, ethical considerations, and health promotion campaigns.",
      "pathwaysConcepts": [
        "3",
        "10"
      ],
      "contactHours": "(3 Lec, 3 Crd)",
      "crossListedWith": [],
      "sourceUrl": "https://catalog.vt.edu/undergraduate/course-descriptions/adv/",
      "catalogYear": "2025-2026"
    },
    {
      "code": "ADV 3004",
      "subject": "ADV",
      "number": "3004",
      "level": 3000,
      "title": "Advertising Copywriting and Brand Storytelling",
      "credits": {
        "min": 3,
        "max": 3
      },
      "isVariableCredit": false,
      "description": "Writing advertising messages for print, broadcast, and online media. Basic design and strategic messaging for visual, verbal, and video storytelling. Promotional and sales appeals for products, services, and causes. Theories of image creation and brand identity. Legal and ethical considerations in paid media.",
      "prerequisites": {
        "rawText": "COMM 2024 and MKTG 3504",
        "referencedCourses": [
          "COMM 2024",
          "MKTG 3504"
        ]
      },
      "pathwaysConcepts": [],
      "contactHours": "(3 Lec, 3 Crd)",
      "crossListedWith": [],
      "sourceUrl": "https://catalog.vt.edu/undergraduate/course-descriptions/adv/",
      "catalogYear": "2025-2026"
    },
    {
      "code": "ADV 3014",
      "subject": "ADV",
      "number": "3014",
      "level": 3000,
      "title": "Account Planning and Media Buying",
      "credits": {
        "min": 3,
        "max": 3
      },
      "isVariableCredit": false,
      "description": "Account planning and media buying in an agency environment. Business and market analysis for advertising clients. Research and assessment strategies for paid-media messages. Management, motivation and persuasion theories in programming. Data analysis, creative briefs, and copy testing. Selection and scheduling of media buys to deliver promotional messages through appropriate communication channels to target audiences efficiently and effectively. Legal and ethical considerations in advertising planning and management.",
      "prerequisites": {
        "rawText": "MKTG 3504",
        "referencedCourses": [
          "MKTG 3504"
        ]
      },
      "pathwaysConcepts": [],
      "contactHours": "(3 Lec, 3 Crd)",
      "crossListedWith": [],
      "sourceUrl": "https://catalog.vt.edu/undergraduate/course-descriptions/adv/",
      "catalogYear": "2025-2026"
    },
    {
      "code": "ADV 3024",
      "subject": "ADV",
      "number": "3024",
      "level": 3000,
      "title": "Ethics and Social Responsibility in Advertising",
      "credits": {
        "min": 3,
        "max": 3
      },
      "isVariableCredit": false,
      "description": "Social and ethical issues in commercial and corporate speech. Government regulations of advertising. Propaganda in business, social, and political communication through history. Influence of advertising on culture, social movements, and gender identity.",
      "prerequisites": {
        "rawText": "MKTG 3504",
        "referencedCourses": [
          "MKTG 3504"
        ]
      },
      "pathwaysConcepts": [],
      "contactHours": "(3 Lec, 3 Crd)",
      "crossListedWith": [],
      "sourceUrl": "https://catalog.vt.edu/undergraduate/course-descriptions/adv/",
      "catalogYear": "2025-2026"
    },
    {
      "code": "ADV 3034",
      "subject": "ADV",
      "number": "3034",
      "level": 3000,
      "title": "Topics in Public Relations and Advertising",
      "credits": {
        "min": 3,
        "max": 3
      },
      "isVariableCredit": false,
      "description": "Selected topics in public relations and advertising. Emphasis on theoretical, practical, or ethical issues in selected contexts. May be repeated 1 time with different content for a maximum of 6 credits.",
      "pathwaysConcepts": [],
      "contactHours": "(3 Lec, 3 Crd)",
      "crossListedWith": [
        "PR 3034"
      ],
      "repeatability": "Repeatability: up to 6 credit hours",
      "sourceUrl": "https://catalog.vt.edu/undergraduate/course-descriptions/adv/",
      "catalogYear": "2025-2026"
    },
    {
      "code": "ADV 4304",
      "subject": "ADV",
      "number": "4304",
      "level": 4000,
      "title": "Advertising Campaigns",
      "credits": {
        "min": 3,
        "max": 3
      },
      "isVariableCredit": false,
      "description": "Culminating course emphasizing application of advertising research, strategy, creative, media, implementation of tactical creative executions, and analyzing knowledge and skills developed throughout major-required coursework. Emphasizes simulating the pitch and execution process through planning, implementing, and evaluating an advertising campaign in response to a client need.",
      "prerequisites": {
        "rawText": "ADV 2034 and ADV 3004 and ADV 3014",
        "referencedCourses": [
          "ADV 2034",
          "ADV 3004",
          "ADV 3014"
        ]
      },
      "pathwaysConcepts": [],
      "contactHours": "(3 Lec, 3 Crd)",
      "crossListedWith": [],
      "sourceUrl": "https://catalog.vt.edu/undergraduate/course-descriptions/adv/",
      "catalogYear": "2025-2026"
    },
    {
      "code": "ADV 4324",
      "subject": "ADV",
      "number": "4324",
      "level": 4000,
      "title": "Health Communication Campaigns",
      "credits": {
        "min": 3,
        "max": 3
      },
      "isVariableCredit": false,
      "description": "Investigates theory-driven, research-based approaches to health message design, audience-centered strategies for health campaign design, and the impact of social media and new communication technologies on health campaigns. Focus on health communicator campaign goals including synthesizing research, understanding the audience, creating engaging and persuasive communication, and delivering messages in ways that raise awareness and increase positive health behaviors. Pre: Senior standing",
      "pathwaysConcepts": [],
      "contactHours": "(3 Lec, 3 Crd)",
      "crossListedWith": [],
      "sourceUrl": "https://catalog.vt.edu/undergraduate/course-descriptions/adv/",
      "catalogYear": "2025-2026"
    },
    {
      "code": "ADV 5204",
      "subject": "ADV",
      "number": "5204",
      "level": 5000,
      "title": "Health Communication",
      "credits": {
        "min": 3,
        "max": 3
      },
      "isVariableCredit": false,
      "description": "Health communication with a focus on application of communication theory to health contexts, including health literacy, patient-provider communication, electronic health and technology; health communication messages and campaigns; impact of media and culture on health; ethical communication. Pre: Graduate standing.",
      "pathwaysConcepts": [],
      "contactHours": "(3 Lec, 3 Crd)",
      "crossListedWith": [],
      "sourceUrl": "https://catalog.vt.edu/undergraduate/course-descriptions/adv/",
      "catalogYear": "2025-2026"
    },
    {
      "code": "ADV 5324G",
      "subject": "ADV",
      "number": "5324G",
      "level": 5000,
      "title": "Advanced Health Communication Campaigns",
      "credits": {
        "min": 3,
        "max": 3
      },
      "isVariableCredit": false,
      "description": "Investigates theory-driven, research-based approaches to health message design, audience-centered strategies for health campaign design, and the impact of social media and new communication technologies on health campaigns. Focus on health communicator campaign goals including synthesizing research, understanding the audience, creating engaging and persuasive communication, and delivering messages in ways that raise awareness and increase positive health behaviors. Pre: Graduate standing",
      "pathwaysConcepts": [],
      "contactHours": "(3 Lec, 3 Crd)",
      "crossListedWith": [],
      "sourceUrl": "https://catalog.vt.edu/undergraduate/course-descriptions/adv/",
      "catalogYear": "2025-2026"
    },
    {
      "code": "ADV 5554",
      "subject": "ADV",
      "number": "5554",
      "level": 5000,
      "title": "Health Communication Campaigns",
      "credits": {
        "min": 3,
        "max": 3
      },
      "isVariableCredit": false,
      "description": "Investigates theory-driven, research-based approaches to health message design, audience-centered strategies for health campaign design, and the impact of social media and new communication technologies on health campaigns. Focus on health communicator campaign goals including synthesizing research, understanding the audience, creating engaging and persuasive communication, and delivering messages in ways that raise awareness and increase positive health behaviors. Pre: Graduate standing",
      "pathwaysConcepts": [],
      "contactHours": "(3 Lec, 3 Crd)",
      "crossListedWith": [],
      "sourceUrl": "https://catalog.vt.edu/undergraduate/course-descriptions/adv/",
      "catalogYear": "2025-2026"
    }
  ]
}